LICENSE
README.md
kutsu/__init__.py
kutsu/expressions.py
kutsu/http_request.py
kutsu/http_server.py
kutsu/state.py
kutsu/util.py
kutsu-0.1.1.dist-info/LICENSE
kutsu-0.1.1.dist-info/METADATA
kutsu-0.1.1.dist-info/WHEEL
kutsu-0.1.1.dist-info/RECORD
